<?xml version="1.0" encoding="UTF-8"?>
<!DOCTYPE mapper PUBLIC "-//mybatis.org//DTD Mapper 3.0//EN" "http://mybatis.org/dtd/mybatis-3-mapper.dtd">
<mapper namespace="com.chaoshi.mapper.PlaylistMapper">

    <!-- 结果集映射 -->
    <resultMap id="BaseResultMap" type="com.chaoshi.entity.Playlist">
        <id column="id" property="id" jdbcType="BIGINT"/>
        <result column="name" property="name" jdbcType="VARCHAR"/>
        <result column="cover" property="coverUrl" jdbcType="VARCHAR"/>
        <result column="description" property="description" jdbcType="LONGVARCHAR"/>
        <result column="user_id" property="userId" jdbcType="BIGINT"/>
        <result column="is_public" property="isPublic" jdbcType="BOOLEAN"/>
        <result column="play_count" property="playCount" jdbcType="BIGINT"/>
        <result column="song_count" property="songCount" jdbcType="INTEGER"/>
        <result column="created_at" property="createdAt" jdbcType="TIMESTAMP"/>
        <result column="updated_at" property="updatedAt" jdbcType="TIMESTAMP"/>
        <result column="deleted" property="deleted" jdbcType="INTEGER"/>
    </resultMap>

    <!-- 基础列 -->
    <sql id="Base_Column_List">
        id, name, cover, description, user_id, is_public, song_count,created_at, updated_at, deleted
    </sql>

    <!-- 插入播放列表 -->
    <insert id="insertPlaylist" parameterType="com.chaoshi.entity.Playlist" useGeneratedKeys="true" keyProperty="id">
        INSERT INTO playlists (name, cover, description, user_id, is_public, created_at, updated_at)
        VALUES (#{name}, #{coverUrl}, #{description}, #{userId}, #{isPublic}, NOW(), NOW())
    </insert>

    <!-- 查询所有播放列表 -->
    <select id="selectAll" resultMap="BaseResultMap">
        SELECT
        <include refid="Base_Column_List"/>
        FROM playlists
        WHERE deleted = 0
        ORDER BY created_at DESC
    </select>

    <!-- 根据ID查询播放列表 -->
    <select id="selectById" parameterType="java.lang.Long" resultMap="BaseResultMap">
        SELECT
        <include refid="Base_Column_List"/>
        FROM playlists
        WHERE id = #{id} AND deleted = 0
    </select>

    <!-- 根据用户ID查询播放列表 -->
    <select id="selectByUserId" parameterType="java.lang.Long" resultMap="BaseResultMap">
        SELECT
        <include refid="Base_Column_List"/>
        FROM playlists
        WHERE user_id = #{userId} AND deleted = 0
        ORDER BY created_at DESC
    </select>

    <!-- 查询公开播放列表 -->
    <select id="selectPublicPlaylists" resultMap="BaseResultMap">
        SELECT
        <include refid="Base_Column_List"/>
        FROM playlists
        WHERE is_public = true AND deleted = 0
        ORDER BY created_at DESC
        LIMIT #{offset}, #{size}
    </select>

    <!-- 分页查询播放列表 -->
    <select id="selectPage" resultMap="BaseResultMap">
        SELECT
        <include refid="Base_Column_List"/>
        FROM playlists
        WHERE deleted = 0
        <if test="name != null and name != ''">
            AND name LIKE CONCAT('%', #{name}, '%')
        </if>
        <if test="userId != null">
            AND user_id = #{userId}
        </if>
        <if test="isPublic != null">
            AND is_public = #{isPublic}
        </if>
        ORDER BY created_at DESC
        LIMIT #{offset}, #{size}
    </select>

    <!-- 统计播放列表数量 -->
    <select id="countPlaylists" resultType="java.lang.Long">
        SELECT COUNT(*)
        FROM playlists
        WHERE deleted = 0
        <if test="name != null and name != ''">
            AND name LIKE CONCAT('%', #{name}, '%')
        </if>
        <if test="userId != null">
            AND user_id = #{userId}
        </if>
        <if test="isPublic != null">
            AND is_public = #{isPublic}
        </if>
    </select>

    <!-- 更新播放列表信息 -->
    <update id="updatePlaylist" parameterType="com.chaoshi.entity.Playlist">
        UPDATE playlists
        <set>
            <if test="name != null and name != ''">
                name = #{name},
            </if>
            <if test="coverUrl != null">
            cover = #{coverUrl},
        </if>
            <if test="description != null">
                description = #{description},
            </if>
            <if test="isPublic != null">
                is_public = #{isPublic},
            </if>
            updated_at = NOW()
        </set>
        WHERE id = #{id} AND deleted = 0
    </update>

    <!-- 逻辑删除播放列表 -->
    <update id="deletePlaylist" parameterType="java.lang.Long">
        UPDATE playlists
        SET deleted = 1, updated_at = NOW()
        WHERE id = #{id} AND deleted = 0
    </update>

    <!-- 搜索播放列表 -->
    <select id="searchPlaylists" resultMap="BaseResultMap">
        SELECT
        <include refid="Base_Column_List"/>
        FROM playlists
        WHERE deleted = 0 AND is_public = true
        AND (name LIKE CONCAT('%', #{keyword}, '%') OR description LIKE CONCAT('%', #{keyword}, '%'))
        ORDER BY
        CASE
            WHEN name LIKE CONCAT(#{keyword}, '%') THEN 1
            WHEN name LIKE CONCAT('%', #{keyword}, '%') THEN 2
            ELSE 3
        END,
        created_at DESC
        LIMIT #{offset}, #{size}
    </select>

</mapper>